{
    "description": "",
    "tags": [],
    "size": {
        "height": 1280,
        "width": 720
    },
    "objects": [
        {
            "id": 14750064,
            "classId": 21171,
            "description": "",
            "geometryType": "rectangle",
            "labelerLogin": "vo@datasetninja.com",
            "createdAt": "2023-07-12T11:52:11.475Z",
            "updatedAt": "2023-07-12T11:52:11.475Z",
            "tags": [],
            "classTitle": "ripe",
            "points": {
                "exterior": [
                    [
                        381,
                        712
                    ],
                    [
                        425,
                        742
                    ]
                ],
                "interior": []
            }
        },
        {
            "id": 14750063,
            "classId": 21176,
            "description": "",
            "geometryType": "rectangle",
            "labelerLogin": "vo@datasetninja.com",
            "createdAt": "2023-07-12T11:52:11.475Z",
            "updatedAt": "2023-07-12T11:52:11.475Z",
            "tags": [],
            "classTitle": "peduncle",
            "points": {
                "exterior": [
                    [
                        365,
                        693
                    ],
                    [
                        416,
                        717
                    ]
                ],
                "interior": []
            }
        }
    ]
}