{
    "description": "",
    "tags": [],
    "size": {
        "height": 480,
        "width": 640
    },
    "objects": [
        {
            "id": 14752607,
            "classId": 21171,
            "description": "",
            "geometryType": "rectangle",
            "labelerLogin": "vo@datasetninja.com",
            "createdAt": "2023-07-12T12:07:59.745Z",
            "updatedAt": "2023-07-12T12:07:59.745Z",
            "tags": [],
            "classTitle": "ripe",
            "points": {
                "exterior": [
                    [
                        270,
                        204
                    ],
                    [
                        346,
                        270
                    ]
                ],
                "interior": []
            }
        },
        {
            "id": 14752606,
            "classId": 21171,
            "description": "",
            "geometryType": "rectangle",
            "labelerLogin": "vo@datasetninja.com",
            "createdAt": "2023-07-12T12:07:59.745Z",
            "updatedAt": "2023-07-12T12:07:59.745Z",
            "tags": [],
            "classTitle": "ripe",
            "points": {
                "exterior": [
                    [
                        72,
                        117
                    ],
                    [
                        134,
                        182
                    ]
                ],
                "interior": []
            }
        },
        {
            "id": 14752605,
            "classId": 21171,
            "description": "",
            "geometryType": "rectangle",
            "labelerLogin": "vo@datasetninja.com",
            "createdAt": "2023-07-12T12:07:59.745Z",
            "updatedAt": "2023-07-12T12:07:59.745Z",
            "tags": [],
            "classTitle": "ripe",
            "points": {
                "exterior": [
                    [
                        0,
                        136
                    ],
                    [
                        58,
                        206
                    ]
                ],
                "interior": []
            }
        },
        {
            "id": 14752604,
            "classId": 21171,
            "description": "",
            "geometryType": "rectangle",
            "labelerLogin": "vo@datasetninja.com",
            "createdAt": "2023-07-12T12:07:59.745Z",
            "updatedAt": "2023-07-12T12:07:59.745Z",
            "tags": [],
            "classTitle": "ripe",
            "points": {
                "exterior": [
                    [
                        39,
                        73
                    ],
                    [
                        85,
                        127
                    ]
                ],
                "interior": []
            }
        },
        {
            "id": 14752603,
            "classId": 21171,
            "description": "",
            "geometryType": "rectangle",
            "labelerLogin": "vo@datasetninja.com",
            "createdAt": "2023-07-12T12:07:59.745Z",
            "updatedAt": "2023-07-12T12:07:59.745Z",
            "tags": [],
            "classTitle": "ripe",
            "points": {
                "exterior": [
                    [
                        105,
                        63
                    ],
                    [
                        145,
                        103
                    ]
                ],
                "interior": []
            }
        },
        {
            "id": 14752602,
            "classId": 21171,
            "description": "",
            "geometryType": "rectangle",
            "labelerLogin": "vo@datasetninja.com",
            "createdAt": "2023-07-12T12:07:59.745Z",
            "updatedAt": "2023-07-12T12:07:59.745Z",
            "tags": [],
            "classTitle": "ripe",
            "points": {
                "exterior": [
                    [
                        201,
                        41
                    ],
                    [
                        245,
                        83
                    ]
                ],
                "interior": []
            }
        },
        {
            "id": 14752601,
            "classId": 21171,
            "description": "",
            "geometryType": "rectangle",
            "labelerLogin": "vo@datasetninja.com",
            "createdAt": "2023-07-12T12:07:59.745Z",
            "updatedAt": "2023-07-12T12:07:59.745Z",
            "tags": [],
            "classTitle": "ripe",
            "points": {
                "exterior": [
                    [
                        19,
                        7
                    ],
                    [
                        82,
                        66
                    ]
                ],
                "interior": []
            }
        },
        {
            "id": 14752600,
            "classId": 21176,
            "description": "",
            "geometryType": "rectangle",
            "labelerLogin": "vo@datasetninja.com",
            "createdAt": "2023-07-12T12:07:59.745Z",
            "updatedAt": "2023-07-12T12:07:59.745Z",
            "tags": [],
            "classTitle": "peduncle",
            "points": {
                "exterior": [
                    [
                        301,
                        161
                    ],
                    [
                        326,
                        221
                    ]
                ],
                "interior": []
            }
        },
        {
            "id": 14752599,
            "classId": 21176,
            "description": "",
            "geometryType": "rectangle",
            "labelerLogin": "vo@datasetninja.com",
            "createdAt": "2023-07-12T12:07:59.745Z",
            "updatedAt": "2023-07-12T12:07:59.745Z",
            "tags": [],
            "classTitle": "peduncle",
            "points": {
                "exterior": [
                    [
                        171,
                        8
                    ],
                    [
                        221,
                        47
                    ]
                ],
                "interior": []
            }
        },
        {
            "id": 14752598,
            "classId": 21176,
            "description": "",
            "geometryType": "rectangle",
            "labelerLogin": "vo@datasetninja.com",
            "createdAt": "2023-07-12T12:07:59.745Z",
            "updatedAt": "2023-07-12T12:07:59.745Z",
            "tags": [],
            "classTitle": "peduncle",
            "points": {
                "exterior": [
                    [
                        7,
                        88
                    ],
                    [
                        86,
                        151
                    ]
                ],
                "interior": []
            }
        },
        {
            "id": 14752597,
            "classId": 21176,
            "description": "",
            "geometryType": "rectangle",
            "labelerLogin": "vo@datasetninja.com",
            "createdAt": "2023-07-12T12:07:59.745Z",
            "updatedAt": "2023-07-12T12:07:59.745Z",
            "tags": [],
            "classTitle": "peduncle",
            "points": {
                "exterior": [
                    [
                        92,
                        19
                    ],
                    [
                        131,
                        73
                    ]
                ],
                "interior": []
            }
        },
        {
            "id": 14752596,
            "classId": 21176,
            "description": "",
            "geometryType": "rectangle",
            "labelerLogin": "vo@datasetninja.com",
            "createdAt": "2023-07-12T12:07:59.745Z",
            "updatedAt": "2023-07-12T12:07:59.745Z",
            "tags": [],
            "classTitle": "peduncle",
            "points": {
                "exterior": [
                    [
                        38,
                        28
                    ],
                    [
                        60,
                        82
                    ]
                ],
                "interior": []
            }
        }
    ]
}